rarefaction/__init__.py
rarefaction/rarefaction.py
rarefaction/version.py
rarefaction/accumulation/__init__.py
rarefaction/accumulation/multi_accumu.py
rarefaction/rarefy_filter/__init__.py
rarefaction/rarefy_filter/binary_dummy.py
rarefaction/rarefy_filter/filter.py
rarefaction/rarefy_filter/rarefy.py
rarefaction/test/__init__.py
rarefaction/test/accumu_test.py
rarefaction-1.2.2.dist-info/LICENSE
rarefaction-1.2.2.dist-info/METADATA
rarefaction-1.2.2.dist-info/WHEEL
rarefaction-1.2.2.dist-info/top_level.txt
rarefaction-1.2.2.dist-info/RECORD
